{
  "404": {
    "css": [
      "/assets/css/0.4e287f0a.css",
      "/assets/css/1.5094ed0b.css",
      "/assets/css/404.c74612bf.css"
    ],
    "js": [
      "/assets/js/0.4e287f0a.chunk.js",
      "/assets/js/1.5094ed0b.chunk.js",
      "/assets/js/404.js"
    ]
  },
  "cart": {
    "css": [
      "/assets/css/0.4e287f0a.css",
      "/assets/css/cart.7e352fac.css"
    ],
    "js": [
      "/assets/js/0.4e287f0a.chunk.js",
      "/assets/js/3.7259d4d0.chunk.js",
      "/assets/js/cart.js"
    ]
  },
  "catalog": {
    "css": [
      "/assets/css/0.4e287f0a.css",
      "/assets/css/1.5094ed0b.css",
      "/assets/css/catalog.1e942aaf.css"
    ],
    "js": [
      "/assets/js/0.4e287f0a.chunk.js",
      "/assets/js/1.5094ed0b.chunk.js",
      "/assets/js/catalog.js"
    ]
  },
  "contacts": {
    "css": [
      "/assets/css/0.4e287f0a.css",
      "/assets/css/2.354b8f0f.css",
      "/assets/css/contacts.baae6d36.css"
    ],
    "js": [
      "/assets/js/0.4e287f0a.chunk.js",
      "/assets/js/2.354b8f0f.chunk.js",
      "/assets/js/contacts.js"
    ]
  },
  "favorite": {
    "css": [
      "/assets/css/0.4e287f0a.css",
      "/assets/css/1.5094ed0b.css",
      "/assets/css/favorite.089c915a.css"
    ],
    "js": [
      "/assets/js/0.4e287f0a.chunk.js",
      "/assets/js/1.5094ed0b.chunk.js",
      "/assets/js/favorite.js"
    ]
  },
  "index": {
    "css": [
      "/assets/css/0.4e287f0a.css",
      "/assets/css/2.354b8f0f.css",
      "/assets/css/index.3016b1a3.css"
    ],
    "js": [
      "/assets/js/0.4e287f0a.chunk.js",
      "/assets/js/2.354b8f0f.chunk.js",
      "/assets/js/index.js"
    ]
  },
  "killreal": {
    "css": "/assets/css/2.354b8f0f.css",
    "js": [
      "/assets/js/2.354b8f0f.chunk.js",
      "/assets/js/killreal.js"
    ]
  },
  "lk": {
    "css": [
      "/assets/css/0.4e287f0a.css",
      "/assets/css/lk.e9858e28.css"
    ],
    "js": [
      "/assets/js/0.4e287f0a.chunk.js",
      "/assets/js/3.7259d4d0.chunk.js",
      "/assets/js/lk.js"
    ]
  },
  "news": {
    "css": [
      "/assets/css/0.4e287f0a.css",
      "/assets/css/1.5094ed0b.css",
      "/assets/css/news.c0dfc75b.css"
    ],
    "js": [
      "/assets/js/0.4e287f0a.chunk.js",
      "/assets/js/1.5094ed0b.chunk.js",
      "/assets/js/news.js"
    ]
  },
  "pages": {
    "js": "/assets/js/pages.js"
  },
  "product": {
    "css": [
      "/assets/css/0.4e287f0a.css",
      "/assets/css/2.354b8f0f.css",
      "/assets/css/product.eec52f0e.css"
    ],
    "js": [
      "/assets/js/0.4e287f0a.chunk.js",
      "/assets/js/2.354b8f0f.chunk.js",
      "/assets/js/product.js"
    ]
  },
  "stocks": {
    "css": [
      "/assets/css/0.4e287f0a.css",
      "/assets/css/1.5094ed0b.css",
      "/assets/css/stocks.d6c1cb1b.css"
    ],
    "js": [
      "/assets/js/0.4e287f0a.chunk.js",
      "/assets/js/1.5094ed0b.chunk.js",
      "/assets/js/stocks.js"
    ]
  }
}